setup.py
zerokspot/__init__.py
zerokspot.recipe.git.egg-info/PKG-INFO
zerokspot.recipe.git.egg-info/SOURCES.txt
zerokspot.recipe.git.egg-info/dependency_links.txt
zerokspot.recipe.git.egg-info/entry_points.txt
zerokspot.recipe.git.egg-info/namespace_packages.txt
zerokspot.recipe.git.egg-info/requires.txt
zerokspot.recipe.git.egg-info/top_level.txt
zerokspot/recipe/__init__.py
zerokspot/recipe/git/__init__.py
zerokspot/recipe/git/tests.py