Metadata-Version: 1.0
Name: zerokspot.recipe.git
Version: 0.5.4
Summary: Simple zc.buildout recipe for sources in a git repository
Home-page: http://github.com/zerok/zerokspot.gitrecipe/
Author: Horst Gutmann
Author-email: zerok@zerokspot.com
License: UNKNOWN
Platform: UNKNOWN
Classifier: Development Status :: 3 - Alpha
Classifier: Environment :: Plugins
Classifier: Framework :: Buildout
Classifier: Intended Audience :: Developers
Classifier: Programming Language :: Python
Classifier: Topic :: Software Development :: Libraries :: Python Modules
Classifier: Topic :: System :: Installation/Setup
Classifier: License :: OSI Approved :: BSD License
